{"version":1,"authentic":true,"fixture":{"fixtureId":18237038,"home":{"name":"France","code":"FRA"},"away":{"name":"Spain","code":"ESP"},"participant1IsHome":true,"competition":"FIFA World Cup 2026","stage":"Semi-final","venue":"","startTime":1784055600000,"finalScore":{"home":0,"away":2}},"director":{"title":"The goal that happened twice","durationMs":90000,"sourceWindow":{"fromTs":1784060350000,"toTs":1784060850000,"compression":6.25},"finalCutAtMs":86000},"provenance":{"captureRepo":"LightCreator1007/steamline","captureCommit":"b3bd417c1e28089c885a5454f654b1caadbde942","capturePaths":["fixtures/live-18237038/18237038/scores.jsonl","fixtures/live-18237038/18237038/odds.jsonl"],"scoreSha256":"ae639893e9a2ee0a3d23d0e18f86fbf3d4ee2e378307f62bd3adf68864261f44","oddsSha256":"1020eb7d8094fca5b0ec88898496d142c0899bb885f34951b0d2c7b2f3256ab5","scoreUrl":"https://raw.githubusercontent.com/LightCreator1007/steamline/b3bd417c1e28089c885a5454f654b1caadbde942/fixtures/live-18237038/18237038/scores.jsonl","oddsUrl":"https://raw.githubusercontent.com/LightCreator1007/steamline/b3bd417c1e28089c885a5454f654b1caadbde942/fixtures/live-18237038/18237038/odds.jsonl","proofRepo":"danySSG/moment-mints","proofCommit":"2f10829f4a4e95c571a72b43eada1088c63642bd","proofLogPath":"mint/proof-log.ndjson","proofLogSha256":"6810cad65784e3a1c79b642a33bb6642ca655e88ab4483fc2aca828bf0f1ff46","proofLogUrl":"https://github.com/danySSG/moment-mints/blob/2f10829f4a4e95c571a72b43eada1088c63642bd/mint/proof-log.ndjson","note":"Public TxLINE capture, reduced deterministically. Proof signatures are commit-pinned archived proof-log records; they are not presented as currently retrievable or chain-verified. Adjacent proof/observed sequences come from independent public captures."},"proofEvidence":[{"seq":618,"observedSeq":619,"statKey":2,"value":2,"event":"GOAL","txSig":"25GkSpdG4zciFc9z4cLUtWmowh9fYrH6YgzTb5GF8eDxZarXbLeDofvQPTK58MuHffE2HFiuAURhAj8zXefFZsKD","network":"devnet","epochDay":20648,"recordStatus":"archived-proof-log-record","explorer":"https://explorer.solana.com/tx/25GkSpdG4zciFc9z4cLUtWmowh9fYrH6YgzTb5GF8eDxZarXbLeDofvQPTK58MuHffE2HFiuAURhAj8zXefFZsKD?cluster=devnet"},{"seq":641,"observedSeq":641,"statKey":2,"value":3,"event":"GOAL","txSig":"34ZXkqc9F44UfeLqqzWhCfshJugDCJsuWTU6SMVduKBh5LBvMdNo3XmvTchrfBZSswCPRXwJyH7XkkpzgyjQVxr","network":"devnet","epochDay":20648,"recordStatus":"archived-proof-log-record","explorer":"https://explorer.solana.com/tx/34ZXkqc9F44UfeLqqzWhCfshJugDCJsuWTU6SMVduKBh5LBvMdNo3XmvTchrfBZSswCPRXwJyH7XkkpzgyjQVxr?cluster=devnet"},{"seq":682,"observedSeq":683,"statKey":2,"value":2,"event":"GOAL_REVOKED","supersedesSeq":641,"txSig":"4EVqXiQztFnDjDPTLyFtfeHRjazNYts9ZYGzHz1cQ8enisUpxPZsdhAVfRsdN2dFfGPe7jaJ2Z6dAaDFvGo1hdWh","network":"devnet","epochDay":20648,"recordStatus":"archived-proof-log-record","explorer":"https://explorer.solana.com/tx/4EVqXiQztFnDjDPTLyFtfeHRjazNYts9ZYGzHz1cQ8enisUpxPZsdhAVfRsdN2dFfGPe7jaJ2Z6dAaDFvGo1hdWh?cluster=devnet"}],"events":[{"kind":"score","atMs":0,"baseline":true,"payload":{"FixtureId":18237038,"Seq":608,"Ts":1784060338746,"StatusId":4,"Action":null,"Clock":{"Running":true,"Seconds":3418},"Stats":{"1":0,"2":1,"3":1,"4":1,"5":0,"6":0,"7":3,"8":1}}},{"kind":"score","atMs":546,"payload":{"FixtureId":18237038,"Seq":610,"Ts":1784060353413,"StatusId":4,"Action":"danger_possession","Clock":{"Running":true,"Seconds":3433},"Stats":{"1":0,"2":1,"3":1,"4":1,"5":0,"6":0,"7":3,"8":1},"Participant":2,"Possession":2,"PossessionType":"DangerPossession"}},{"kind":"score","atMs":1461,"payload":{"FixtureId":18237038,"Seq":612,"Ts":1784060359130,"StatusId":4,"Action":"shot","Clock":{"Running":true,"Seconds":3437},"Stats":{"1":0,"2":1,"3":1,"4":1,"5":0,"6":0,"7":3,"8":1},"Data":{"Outcome":"Blocked"},"Participant":2}},{"kind":"score","atMs":2198,"payload":{"FixtureId":18237038,"Seq":614,"Ts":1784060363740,"StatusId":4,"Action":"attack_possession","Clock":{"Running":true,"Seconds":3443},"Stats":{"1":0,"2":1,"3":1,"4":1,"5":0,"6":0,"7":3,"8":1},"Participant":2,"Possession":2,"PossessionType":"AttackPossession"}},{"kind":"odds","atMs":3404,"payload":{"FixtureId":18237038,"MessageId":"1837789657:00003:000264-10021-stab","Ts":1784060371276,"InRunning":true,"SuperOddsType":"1X2_PARTICIPANT_RESULT","PriceNames":["part1","draw","part2"],"Pct":["14.231","28.058","57.703"]}},{"kind":"score","atMs":3740,"payload":{"FixtureId":18237038,"Seq":615,"Ts":1784060373377,"StatusId":4,"Action":"high_danger_possession","Clock":{"Running":true,"Seconds":3453},"Stats":{"1":0,"2":1,"3":1,"4":1,"5":0,"6":0,"7":3,"8":1},"Participant":2,"Possession":2,"PossessionType":"HighDangerPossession"}},{"kind":"score","atMs":3831,"payload":{"FixtureId":18237038,"Seq":616,"Ts":1784060373945,"StatusId":4,"Action":"possible","Clock":{"Running":true,"Seconds":3453},"Stats":{"1":0,"2":1,"3":1,"4":1,"5":0,"6":0,"7":3,"8":1},"Data":{"Corner":false,"Goal":true,"Penalty":false},"Participant":2}},{"kind":"score","atMs":4164,"payload":{"FixtureId":18237038,"Seq":617,"Ts":1784060376027,"StatusId":4,"Action":"goal","Clock":{"Running":true,"Seconds":3455},"Stats":{"1":0,"2":1,"3":1,"4":1,"5":0,"6":0,"7":3,"8":1},"Data":{},"Participant":2}},{"kind":"odds","atMs":11204,"payload":{"FixtureId":18237038,"MessageId":"1837789746:00003:000021-10021-stab","Ts":1784060420024,"InRunning":true,"SuperOddsType":"1X2_PARTICIPANT_RESULT","PriceNames":["part1","draw","part2"],"Pct":["3.401","10.599","85.985"]}},{"kind":"score","atMs":20528,"payload":{"FixtureId":18237038,"Seq":619,"Ts":1784060478302,"StatusId":4,"Action":"possible","Clock":{"Running":true,"Seconds":3455},"Stats":{"1":0,"2":2,"3":1,"4":1,"5":0,"6":0,"7":3,"8":1},"Data":{"Corner":false,"Goal":false,"Penalty":false},"Participant":2}},{"kind":"score","atMs":20984,"payload":{"FixtureId":18237038,"Seq":620,"Ts":1784060481148,"StatusId":4,"Action":"goal","Clock":{"Running":true,"Seconds":3455},"Stats":{"1":0,"2":2,"3":1,"4":1,"5":0,"6":0,"7":3,"8":1},"Data":{"GoalType":"Shot","PlayerId":907005},"Participant":2}},{"kind":"score","atMs":21056,"payload":{"FixtureId":18237038,"Seq":621,"Ts":1784060481602,"StatusId":4,"Action":"standby","Clock":{"Running":true,"Seconds":3455},"Stats":{"1":0,"2":2,"3":1,"4":1,"5":0,"6":0,"7":3,"8":1}}},{"kind":"score","atMs":21104,"payload":{"FixtureId":18237038,"Seq":622,"Ts":1784060481899,"StatusId":4,"Action":"kickoff","Clock":{"Running":true,"Seconds":3561},"Stats":{"1":0,"2":2,"3":1,"4":1,"5":0,"6":0,"7":3,"8":1},"Possession":1}},{"kind":"score","atMs":21426,"payload":{"FixtureId":18237038,"Seq":625,"Ts":1784060483915,"StatusId":4,"Action":"attack_possession","Clock":{"Running":true,"Seconds":3563},"Stats":{"1":0,"2":2,"3":1,"4":1,"5":0,"6":0,"7":3,"8":1},"Participant":2,"Possession":2,"PossessionType":"AttackPossession"}},{"kind":"score","atMs":22133,"payload":{"FixtureId":18237038,"Seq":626,"Ts":1784060488332,"StatusId":4,"Action":"possession","Clock":{"Running":true,"Seconds":3567},"Stats":{"1":0,"2":2,"3":1,"4":1,"5":0,"6":0,"7":3,"8":1},"Participant":1,"Possession":1}},{"kind":"score","atMs":22172,"payload":{"FixtureId":18237038,"Seq":627,"Ts":1784060488574,"StatusId":4,"Action":"safe_possession","Clock":{"Running":true,"Seconds":3568},"Stats":{"1":0,"2":2,"3":1,"4":1,"5":0,"6":0,"7":3,"8":1},"Participant":1,"Possession":1,"PossessionType":"SafePossession"}},{"kind":"odds","atMs":23113,"payload":{"FixtureId":18237038,"MessageId":"1837789869:00003:000365-1-10021-stab","Ts":1784060494458,"InRunning":true,"SuperOddsType":"1X2_PARTICIPANT_RESULT","PriceNames":["part1","draw","part2"],"Pct":["3.650","11.055","85.324"]}},{"kind":"score","atMs":27725,"payload":{"FixtureId":18237038,"Seq":631,"Ts":1784060523280,"StatusId":4,"Action":"possession","Clock":{"Running":true,"Seconds":3602},"Stats":{"1":0,"2":2,"3":1,"4":1,"5":0,"6":0,"7":3,"8":1},"Participant":2,"Possession":2}},{"kind":"score","atMs":29478,"payload":{"FixtureId":18237038,"Seq":634,"Ts":1784060534237,"StatusId":4,"Action":"safe_possession","Clock":{"Running":true,"Seconds":3613},"Stats":{"1":0,"2":2,"3":1,"4":1,"5":0,"6":0,"7":3,"8":1},"Participant":2,"Possession":2,"PossessionType":"SafePossession"}},{"kind":"score","atMs":31035,"payload":{"FixtureId":18237038,"Seq":635,"Ts":1784060543966,"StatusId":4,"Action":"attack_possession","Clock":{"Running":true,"Seconds":3623},"Stats":{"1":0,"2":2,"3":1,"4":1,"5":0,"6":0,"7":3,"8":1},"Participant":2,"Possession":2,"PossessionType":"AttackPossession"}},{"kind":"score","atMs":31275,"payload":{"FixtureId":18237038,"Seq":636,"Ts":1784060545470,"StatusId":4,"Action":"possible","Clock":{"Running":true,"Seconds":3625},"Stats":{"1":0,"2":2,"3":1,"4":1,"5":0,"6":0,"7":3,"8":1},"Data":{"Corner":false,"Goal":true,"Penalty":false},"Participant":2}},{"kind":"score","atMs":31420,"payload":{"FixtureId":18237038,"Seq":637,"Ts":1784060546373,"StatusId":4,"Action":"high_danger_possession","Clock":{"Running":true,"Seconds":3625},"Stats":{"1":0,"2":2,"3":1,"4":1,"5":0,"6":0,"7":3,"8":1},"Participant":2,"Possession":2,"PossessionType":"HighDangerPossession"}},{"kind":"odds","atMs":31437,"payload":{"FixtureId":18237038,"MessageId":"1837789973:00003:000170-1-10021-stab","Ts":1784060546479,"InRunning":true,"SuperOddsType":"1X2_PARTICIPANT_RESULT","PriceNames":["part1","draw","part2"],"Pct":["3.378","10.542","86.059"]}},{"kind":"score","atMs":31993,"payload":{"FixtureId":18237038,"Seq":638,"Ts":1784060549958,"StatusId":4,"Action":"goal","Clock":{"Running":true,"Seconds":3629},"Stats":{"1":0,"2":2,"3":1,"4":1,"5":0,"6":0,"7":3,"8":1},"Data":{},"Participant":2}},{"kind":"score","atMs":34058,"payload":{"FixtureId":18237038,"Seq":640,"Ts":1784060562861,"StatusId":4,"Action":"var","Clock":{"Running":true,"Seconds":3641},"Stats":{"1":0,"2":2,"3":1,"4":1,"5":0,"6":0,"7":3,"8":1},"Data":{"Type":"Goal"}}},{"kind":"score","atMs":35795,"payload":{"FixtureId":18237038,"Seq":641,"Ts":1784060573720,"StatusId":4,"Action":"var_end","Clock":{"Running":true,"Seconds":3653},"Stats":{"1":0,"2":3,"3":1,"4":1,"5":0,"6":0,"7":3,"8":1},"Data":{"Outcome":"Overturned"}}},{"kind":"score","atMs":36097,"payload":{"FixtureId":18237038,"Seq":642,"Ts":1784060575609,"Action":"action_discarded","Stats":{"1":0,"2":3,"3":1,"4":1,"5":0,"6":0,"7":3,"8":1},"Data":{},"Possession":2,"PossessionType":"HighDangerPossession"}},{"kind":"score","atMs":36514,"payload":{"FixtureId":18237038,"Seq":644,"Ts":1784060578214,"StatusId":4,"Action":"free_kick","Clock":{"Running":true,"Seconds":3657},"Stats":{"1":0,"2":3,"3":1,"4":1,"5":0,"6":0,"7":3,"8":1},"Data":{"FreeKickType":"Offside"},"Participant":1,"Possession":1}},{"kind":"score","atMs":36715,"payload":{"FixtureId":18237038,"Seq":645,"Ts":1784060579469,"StatusId":4,"Action":"attack_possession","Clock":{"Running":true,"Seconds":3659},"Stats":{"1":0,"2":3,"3":1,"4":1,"5":0,"6":0,"7":3,"8":1},"Participant":1,"Possession":1,"PossessionType":"AttackPossession"}},{"kind":"score","atMs":37121,"payload":{"FixtureId":18237038,"Seq":648,"Ts":1784060582005,"StatusId":4,"Action":"possible","Clock":{"Running":true,"Seconds":3661},"Stats":{"1":0,"2":3,"3":1,"4":1,"5":0,"6":0,"7":3,"8":1},"Data":{"Corner":false,"Goal":false,"Penalty":false},"Participant":2}},{"kind":"score","atMs":37457,"payload":{"FixtureId":18237038,"Seq":649,"Ts":1784060584109,"StatusId":4,"Action":"possession","Clock":{"Running":true,"Seconds":3663},"Stats":{"1":0,"2":3,"3":1,"4":1,"5":0,"6":0,"7":3,"8":1},"Participant":2,"Possession":2}},{"kind":"score","atMs":41306,"payload":{"FixtureId":18237038,"Seq":652,"Ts":1784060608164,"StatusId":4,"Action":"throw_in","Clock":{"Running":true,"Seconds":3675},"Stats":{"1":0,"2":3,"3":1,"4":1,"5":0,"6":0,"7":3,"8":1},"Data":{"ThrowInType":"Attack"},"Participant":1,"Possession":1}},{"kind":"score","atMs":41852,"payload":{"FixtureId":18237038,"Seq":653,"Ts":1784060611574,"StatusId":4,"Action":"safe_possession","Clock":{"Running":true,"Seconds":3691},"Stats":{"1":0,"2":3,"3":1,"4":1,"5":0,"6":0,"7":3,"8":1},"Participant":1,"Possession":1,"PossessionType":"SafePossession"}},{"kind":"odds","atMs":42813,"payload":{"FixtureId":18237038,"MessageId":"1837790117:00003:000127-10021-stab","Ts":1784060617584,"InRunning":true,"SuperOddsType":"1X2_PARTICIPANT_RESULT","PriceNames":["part1","draw","part2"],"Pct":["2.985","10.034","86.957"]}},{"kind":"score","atMs":44988,"payload":{"FixtureId":18237038,"Seq":656,"Ts":1784060631173,"StatusId":4,"Action":"throw_in","Clock":{"Running":true,"Seconds":3709},"Stats":{"1":0,"2":3,"3":1,"4":1,"5":0,"6":0,"7":3,"8":1},"Data":{"ThrowInType":"Safe"},"Participant":2,"Possession":2}},{"kind":"score","atMs":48418,"payload":{"FixtureId":18237038,"Seq":661,"Ts":1784060652613,"StatusId":4,"Action":"possession","Clock":{"Running":true,"Seconds":3732},"Stats":{"1":0,"2":3,"3":1,"4":1,"5":0,"6":0,"7":3,"8":1},"Participant":2,"Possession":2}},{"kind":"score","atMs":49454,"payload":{"FixtureId":18237038,"Seq":663,"Ts":1784060659086,"StatusId":4,"Action":"danger_possession","Clock":{"Running":true,"Seconds":3738},"Stats":{"1":0,"2":3,"3":1,"4":1,"5":0,"6":0,"7":3,"8":1},"Participant":2,"Possession":2,"PossessionType":"DangerPossession"}},{"kind":"score","atMs":50607,"payload":{"FixtureId":18237038,"Seq":665,"Ts":1784060666295,"StatusId":4,"Action":"safe_possession","Clock":{"Running":true,"Seconds":3745},"Stats":{"1":0,"2":3,"3":1,"4":1,"5":0,"6":0,"7":3,"8":1},"Participant":2,"Possession":2,"PossessionType":"SafePossession"}},{"kind":"score","atMs":51346,"payload":{"FixtureId":18237038,"Seq":666,"Ts":1784060670911,"StatusId":4,"Action":"attack_possession","Clock":{"Running":true,"Seconds":3750},"Stats":{"1":0,"2":3,"3":1,"4":1,"5":0,"6":0,"7":3,"8":1},"Participant":2,"Possession":2,"PossessionType":"AttackPossession"}},{"kind":"odds","atMs":52018,"payload":{"FixtureId":18237038,"MessageId":"1837790219:00003:000042-10021-stab","Ts":1784060675115,"InRunning":true,"SuperOddsType":"1X2_PARTICIPANT_RESULT","PriceNames":["part1","draw","part2"],"Pct":["2.882","9.804","87.336"]}},{"kind":"score","atMs":59553,"payload":{"FixtureId":18237038,"Seq":673,"Ts":1784060722207,"StatusId":4,"Action":"danger_possession","Clock":{"Running":true,"Seconds":3801},"Stats":{"1":0,"2":3,"3":1,"4":1,"5":0,"6":0,"7":3,"8":1},"Participant":2,"Possession":2,"PossessionType":"DangerPossession"}},{"kind":"score","atMs":60262,"payload":{"FixtureId":18237038,"Seq":674,"Ts":1784060726637,"StatusId":4,"Action":"attack_possession","Clock":{"Running":true,"Seconds":3806},"Stats":{"1":0,"2":3,"3":1,"4":1,"5":0,"6":0,"7":3,"8":1},"Participant":2,"Possession":2,"PossessionType":"AttackPossession"}},{"kind":"odds","atMs":61890,"payload":{"FixtureId":18237038,"MessageId":"1837790338:00003:000459-10021-stab","Ts":1784060736813,"InRunning":true,"SuperOddsType":"1X2_PARTICIPANT_RESULT","PriceNames":["part1","draw","part2"],"Pct":["2.770","9.434","87.796"]}},{"kind":"score","atMs":62341,"payload":{"FixtureId":18237038,"Seq":676,"Ts":1784060739629,"StatusId":4,"Action":"safe_possession","Clock":{"Running":true,"Seconds":3819},"Stats":{"1":0,"2":3,"3":1,"4":1,"5":0,"6":0,"7":3,"8":1},"Participant":2,"Possession":2,"PossessionType":"SafePossession"}},{"kind":"score","atMs":63658,"payload":{"FixtureId":18237038,"Seq":678,"Ts":1784060747861,"StatusId":4,"Action":"attack_possession","Clock":{"Running":true,"Seconds":3827},"Stats":{"1":0,"2":3,"3":1,"4":1,"5":0,"6":0,"7":3,"8":1},"Participant":1,"Possession":1,"PossessionType":"AttackPossession"}},{"kind":"score","atMs":67873,"payload":{"FixtureId":18237038,"Seq":683,"Ts":1784060774205,"StatusId":4,"Action":"danger_possession","Clock":{"Running":true,"Seconds":3853},"Stats":{"1":0,"2":2,"3":1,"4":1,"5":0,"6":0,"7":4,"8":1},"Participant":1,"Possession":1,"PossessionType":"DangerPossession"}},{"kind":"score","atMs":69930,"payload":{"FixtureId":18237038,"Seq":688,"Ts":1784060787062,"StatusId":4,"Action":"corner","Clock":{"Running":true,"Seconds":3858},"Stats":{"1":0,"2":2,"3":1,"4":1,"5":0,"6":0,"7":5,"8":1},"Participant":1,"Possession":1}},{"kind":"score","atMs":71392,"payload":{"FixtureId":18237038,"Seq":690,"Ts":1784060796199,"StatusId":4,"Action":"high_danger_possession","Clock":{"Running":true,"Seconds":3875},"Stats":{"1":0,"2":2,"3":1,"4":1,"5":0,"6":0,"7":5,"8":1},"Participant":1,"Possession":1,"PossessionType":"HighDangerPossession"}},{"kind":"score","atMs":71924,"payload":{"FixtureId":18237038,"Seq":691,"Ts":1784060799522,"StatusId":4,"Action":"possible","Clock":{"Running":true,"Seconds":3879},"Stats":{"1":0,"2":2,"3":1,"4":1,"5":0,"6":0,"7":5,"8":1},"Data":{"Corner":false,"Goal":false,"Penalty":false},"Participant":1}},{"kind":"score","atMs":72007,"payload":{"FixtureId":18237038,"Seq":692,"Ts":1784060800045,"StatusId":4,"Action":"possession","Clock":{"Running":true,"Seconds":3879},"Stats":{"1":0,"2":2,"3":1,"4":1,"5":0,"6":0,"7":5,"8":1},"Participant":2,"Possession":2}},{"kind":"odds","atMs":72022,"payload":{"FixtureId":18237038,"MessageId":"1837790450:00003:000259-10021-stab","Ts":1784060800138,"InRunning":true,"SuperOddsType":"1X2_PARTICIPANT_RESULT","PriceNames":["part1","draw","part2"],"Pct":["2.747","9.434","87.873"]}},{"kind":"score","atMs":72233,"payload":{"FixtureId":18237038,"Seq":694,"Ts":1784060801455,"StatusId":4,"Action":"goal_kick","Clock":{"Running":true,"Seconds":3881},"Stats":{"1":0,"2":2,"3":1,"4":1,"5":0,"6":0,"7":5,"8":1},"Participant":2,"Possession":2,"PossessionType":"SafePossession"}},{"kind":"score","atMs":75575,"payload":{"FixtureId":18237038,"Seq":697,"Ts":1784060822343,"StatusId":4,"Action":"free_kick","Clock":{"Running":true,"Seconds":3901},"Stats":{"1":0,"2":2,"3":1,"4":1,"5":0,"6":0,"7":5,"8":1},"Data":{"FreeKickType":"Safe"},"Participant":2,"Possession":2}},{"kind":"score","atMs":77581,"payload":{"FixtureId":18237038,"Seq":699,"Ts":1784060834879,"StatusId":4,"Action":"attack_possession","Clock":{"Running":true,"Seconds":3914},"Stats":{"1":0,"2":2,"3":1,"4":1,"5":0,"6":0,"7":5,"8":1},"Participant":2,"Possession":2,"PossessionType":"AttackPossession"}},{"kind":"score","atMs":78292,"payload":{"FixtureId":18237038,"Seq":700,"Ts":1784060839326,"StatusId":4,"Action":"possession","Clock":{"Running":true,"Seconds":3918},"Stats":{"1":0,"2":2,"3":1,"4":1,"5":0,"6":0,"7":5,"8":1},"Participant":1,"Possession":1}},{"kind":"score","atMs":86000,"directorCut":true,"payload":{"FixtureId":18237038,"Seq":1026,"Ts":1784063054751,"StatusId":100,"Action":"game_finalised","Stats":{"1":0,"2":2,"3":2,"4":1,"5":0,"6":0,"7":7,"8":1}}}],"packageHash":"83cc7c4266f44a2272f80deb4bcecbc97be997939ac8bc9041b233728df3c25c"}